pycodestats/__init__.py
pycodestats/main.py
pycodestats-0.5.0.dist-info/LICENSE
pycodestats-0.5.0.dist-info/METADATA
pycodestats-0.5.0.dist-info/WHEEL
pycodestats-0.5.0.dist-info/entry_points.txt
pycodestats-0.5.0.dist-info/top_level.txt
pycodestats-0.5.0.dist-info/RECORD
