Metadata-Version: 2.1
Name: pycodestats
Version: 0.5.0
Summary: A tool to count lines of code in a Python project
Home-page: https://github.com/sammrai/pycodestats
Author: sammrai
Author-email: saku0aab@gmail.com
License: MIT
Project-URL: Homepage, https://github.com/sammrai/pycodestats
Project-URL: Documentation, https://github.com/sammrai/pycodestats
Project-URL: Source, https://github.com/sammrai/pycodestats
Project-URL: Tracker, https://github.com/sammrai/pycodestats/issues
Classifier: Development Status :: 3 - Alpha
Classifier: Programming Language :: Python :: 3
Classifier: Programming Language :: Python :: 3.6
Classifier: Programming Language :: Python :: 3.7
Classifier: Programming Language :: Python :: 3.8
Classifier: License :: OSI Approved :: MIT License
Classifier: Operating System :: OS Independent
Requires-Python: >=3.6
License-File: LICENSE
Requires-Dist: jsonschema >=3.2
